[{"vendorID":"EvolutionGaming","currency":"EUR","amount":516947.50,"displayName":"Aaaaaaaa.A","countryCode":"UA","dateTime":"0001-01-01T00:00:00","gameID":null,"firstName":null,"surName":null},{"vendorID":"EvolutionGaming","currency":"EUR","amount":258427.50,"displayName":"TEST.T","countryCode":"MT","dateTime":"0001-01-01T00:00:00","gameID":null,"firstName":null,"surName":null},{"vendorID":"EvolutionGaming","currency":"EUR","amount":4520.45,"displayName":"Aaaaaaaa.A","countryCode":"UA","dateTime":"0001-01-01T00:00:00","gameID":null,"firstName":null,"surName":null},{"vendorID":"EvolutionGaming","currency":"EUR","amount":3455.00,"displayName":"TEST.T","countryCode":"MT","dateTime":"0001-01-01T00:00:00","gameID":null,"firstName":null,"surName":null},{"vendorID":"EvolutionGaming","currency":"EUR","amount":3270.25,"displayName":"TEST.T","countryCode":"MT","dateTime":"0001-01-01T00:00:00","gameID":null,"firstName":null,"surName":null},{"vendorID":"EvolutionGaming","currency":"EUR","amount":3070.00,"displayName":"TEST.T","countryCode":"MT","dateTime":"0001-01-01T00:00:00","gameID":null,"firstName":null,"surName":null},{"vendorID":"EvolutionGaming","currency":"EUR","amount":2956.00,"displayName":"Aaaaaaaa.A","countryCode":"UA","dateTime":"0001-01-01T00:00:00","gameID":null,"firstName":null,"surName":null},{"vendorID":"EvolutionGaming","currency":"EUR","amount":1628.00,"displayName":"Aaaaaaaa.A","countryCode":"UA","dateTime":"0001-01-01T00:00:00","gameID":null,"firstName":null,"surName":null}]