<?xml version="1.0" encoding="utf-8"?>
<root>
  <node id="BACCARAT" type="category" label="Baccarat" isBranch="true">
    <node label="French Roulette La Partage II" type="" vendor="NetEnt" id="8459000002" categories="ROULETTE" platforms="PC" />
    <node label="European Roulette" type="" vendor="EvolutionGaming" id="8345030905" categories="ROULETTE" platforms="iPad,iPhone,Android" />
    <node label="Auto Roulette La Partage" type="" vendor="NetEnt" id="8455001004" categories="ROULETTE" platforms="PC" />
    <node label="Auto Roulette La Partage" type="" vendor="NetEnt" id="8455001005" categories="ROULETTE" platforms="PC" />
    <node label="Auto Roulette" type="" vendor="NetEnt" id="8454001004" categories="ROULETTE" platforms="PC" />
    <node label="French Auto Roulette" type="" vendor="NetEnt" id="8456001005" categories="ROULETTE" platforms="PC" />
    <node label="European Roulette VIP" type="" vendor="EvolutionGaming" id="8345041921" categories="ROULETTE" platforms="iPad,iPhone,Android" />
    <node label="French Auto Roulette La Partage" type="" vendor="NetEnt" id="8457001004" categories="ROULETTE" platforms="PC" />
    <node label="French Auto Roulette" type="" vendor="NetEnt" id="8456001004" categories="ROULETTE" platforms="PC" />
    <node label="Roulette La Partage II" type="" vendor="NetEnt" id="8461000002" categories="ROULETTE" platforms="PC" />
    <node label="French Roulette II" type="" vendor="NetEnt" id="8458000002" categories="ROULETTE" platforms="PC" />
    <node label="Roulette II" type="" vendor="NetEnt" id="8460000002" categories="ROULETTE" platforms="PC" />
  </node>
  <node id="BLACKJACK" type="category" label="BlackJack" isBranch="true">
    <node label="French Roulette" type="" vendor="EvolutionGaming" id="8345090584" categories="ROULETTE" platforms="iPad,iPhone,Android" />
    <node label="Auto roulette" type="" vendor="EvolutionGaming" id="8345022240" categories="ROULETTE" platforms="iPad,iPhone,Android" />
    <node label="Blackjack Common Draw" type="" vendor="NetEnt" id="8441000104" categories="BLACKJACK" platforms="PC" />
  </node>
  <node id="HOLDEM" type="category" label="Casino Hold'em" isBranch="true">
    <node label="Blackjack VIP E" type="" vendor="EvolutionGaming" id="8342042586" categories="BLACKJACK" platforms="iPad,iPhone,Android" />
    <node label="Turkish Roulette" type="" vendor="EvolutionGaming" id="8345098240" categories="ROULETTE" platforms="iPad,iPhone,Android" />
  </node>
  <node id="POKER" type="category" label="Poker" isBranch="true" />
  <node id="ROULETTE" type="category" label="Roulette" isBranch="true">
    <node label="Blackjack VIP A" type="" vendor="EvolutionGaming" id="8342039994" categories="BLACKJACK" platforms="iPad,iPhone,Android" />
    <node label="French Auto Roulette La Partage" type="" vendor="NetEnt" id="8457001005" categories="ROULETTE" platforms="PC" />
  </node>
  <node id="SICBO" type="category" label="Sic Bo" isBranch="true" />
  <node id="LiveGames" type="category" label="Live Games" isBranch="true">
    <node label="French Roulette" type="" vendor="EvolutionGaming" id="8345090584" categories="ROULETTE" platforms="iPad,iPhone,Android" />
    <node label="Blackjack VIP B" type="" vendor="EvolutionGaming" id="8342026961" categories="BLACKJACK" platforms="iPad,iPhone,Android" />
    <node label="Blackjack H" type="" vendor="EvolutionGaming" id="8342017912" categories="BLACKJACK" platforms="iPad,iPhone,Android" />
    <node label="Blackjack H" type="" vendor="EvolutionGaming" id="8342017912" categories="BLACKJACK" platforms="iPad,iPhone,Android" />
    <node label="Auto Roulette La Partage" type="" vendor="NetEnt" id="8455001004" categories="ROULETTE" platforms="PC" />
  </node>
</root>